aoe2_ai_fmt-0.2.data/scripts/format.py
performat/__init__.py
performat/comment_spooler.py
performat/formatted_per_listener.py
performat/formatter.py
performat/perparse/PERLexer.py
performat/perparse/PERListener.py
performat/perparse/PERParser.py
performat/perparse/__init__.py
aoe2_ai_fmt-0.2.dist-info/LICENSE.txt
aoe2_ai_fmt-0.2.dist-info/METADATA
aoe2_ai_fmt-0.2.dist-info/WHEEL
aoe2_ai_fmt-0.2.dist-info/top_level.txt
aoe2_ai_fmt-0.2.dist-info/RECORD
