Metadata-Version: 2.1
Name: aoe2-ai-fmt
Version: 0.2
Summary: A formatter for AoE2 AI rule files (.per).
Home-page: https://github.com/ks07/aoe2-ai-fmt
Author: George Field
Author-email: george@cucurbit.dev
License: UNKNOWN
Platform: UNKNOWN
Classifier: Programming Language :: Python :: 3
Classifier: Programming Language :: Python :: 3 :: Only
Classifier: License :: OSI Approved :: MIT License
Classifier: Operating System :: OS Independent
Classifier: Topic :: Software Development
Classifier: Development Status :: 3 - Alpha
Requires-Python: >=3.6
Requires-Dist: antlr4-python3-runtime (==4.8)
